{
    "web":
    {
        "client_id":"153898838167-m0bcp67fk0o3fibg6ofqjaajh2797u94.apps.googleusercontent.com",
        "project_id":"item-catalog-225600", 
        "auth_uri":"https://accounts.google.com/o/oauth2/auth", 
        "token_uri":"https://www.googleapis.com/oauth2/v3/token",
        "auth_provider_x509_cert_url":"https://www.googleapis.com/oauth2/v1/certs",
        "client_secret":"dCmcy4sNUH1AJLH55P0JV-yX",
        "redirect_uris":["http://localhost:8000/login","http://localhost:8000/gconnect"],
        "javascript_origins":["http://localhost:8000"]}}